LICENSE
MANIFEST.in
README.md
setup.cfg
setup.py
test_flask_share.py
flask_share/__init__.py
flask_share/static/css/share.min.css
flask_share/static/fonts/iconfont.eot
flask_share/static/fonts/iconfont.svg
flask_share/static/fonts/iconfont.ttf
flask_share/static/fonts/iconfont.woff
flask_share/static/js/jquery.share.min.js
flask_share/static/js/social-share.min.js
spring371327.egg-info/PKG-INFO
spring371327.egg-info/SOURCES.txt
spring371327.egg-info/dependency_links.txt
spring371327.egg-info/not-zip-safe
spring371327.egg-info/requires.txt
spring371327.egg-info/top_level.txt