Metadata-Version: 2.1
Name: spring371327
Version: 0.1.0
Summary: create social share component in Jinja2 template based on share.js
Home-page: https://github.com/wangjibao1995/FLASK-SHARE
Author: Jibao Wang
Author-email: wangjibao@iie.ac.cn
License: MIT
Keywords: flask extension development
Platform: any
Classifier: Development status :: 3 - Alpha
Classifier: Environment :: Web Environment
Classifier: Intended Audience :: Developers
Classifier: License :: OSI Approved :: MIT License
Classifier: Programming Language :: Python
Classifier: Programming Language :: Python :: 2
Classifier: Programming Language :: Python :: 2.7
Classifier: Programming Language :: Python :: 3
Classifier: Programming Language :: Python :: 3.3
Classifier: Programming Language :: Python :: 3.4
Classifier: Programming Language :: Python :: 3.5
Classifier: Programming Language :: Python :: 3.6
Classifier: Programming Language :: Python :: 3.7
Classifier: Topic :: Internet :: WWW/HTTP :: Dynamic Content
Classifier: Topic :: Software Development :: Libraries :: Python Modules
